pysense/__init__.py
pysense/apps.py
pysense/command_line.py
pysense/status.py
pysense/users.py
qsense/__init__.py
qsense/ad.py
qsense/apps.py
qsense/command_line.py
qsense/custom_property.py
qsense/dataconnection.py
qsense/flycheck_apps.py
qsense/flycheck_command_line.py
qsense/license.py
qsense/mail.py
qsense/reloadtask.py
qsense/status.py
qsense/systemrule.py
qsense/users.py
qsense/utils.py
qsense-0.8.4.dist-info/LICENSE
qsense-0.8.4.dist-info/METADATA
qsense-0.8.4.dist-info/WHEEL
qsense-0.8.4.dist-info/entry_points.txt
qsense-0.8.4.dist-info/top_level.txt
qsense-0.8.4.dist-info/RECORD
