Metadata-Version: 2.1
Name: qsense
Version: 0.8.4
Summary: qsense is a python library and a command line tool for qliksense
Home-page: https://github.com/matteoredaelli/qsense
Author: Matteo Redaelli
Author-email: matteo.redaelli@gmail.com
License: GPL
Classifier: Programming Language :: Python :: 3
Classifier: Operating System :: OS Independent
Requires-Python: >=3.6
License-File: LICENSE
Requires-Dist: fire
Requires-Dist: pyqlikengine
Requires-Dist: pytz
Requires-Dist: qsapi
Requires-Dist: requests
Requires-Dist: requests-ntlm
